thirtykn.py
thirtykn-1.0.0.dist-info/LICENSE
thirtykn-1.0.0.dist-info/METADATA
thirtykn-1.0.0.dist-info/WHEEL
thirtykn-1.0.0.dist-info/top_level.txt
thirtykn-1.0.0.dist-info/RECORD
