Metadata-Version: 2.2
Name: thirtykn
Version: 1.0.0
Summary: 30KN: Unicode-based high-compression numeral system combining Hangul and Hanja for 30,000-radix encoding.
Home-page: https://github.com/blueradiance/30kn
Author: blueradiance
Author-email: none@example.com
Classifier: Programming Language :: Python :: 3
Classifier: License :: Other/Proprietary License
Classifier: Operating System :: OS Independent
Requires-Python: >=3.6
License-File: LICENSE
Dynamic: author
Dynamic: author-email
Dynamic: classifier
Dynamic: description
Dynamic: description-content-type
Dynamic: home-page
Dynamic: requires-python
Dynamic: summary
